hmac_signature/__init__.py
hmac_signature/singature.py
hmac_signature-0.2.dist-info/DESCRIPTION.rst
hmac_signature-0.2.dist-info/METADATA
hmac_signature-0.2.dist-info/RECORD
hmac_signature-0.2.dist-info/WHEEL
hmac_signature-0.2.dist-info/metadata.json
hmac_signature-0.2.dist-info/top_level.txt
