Metadata-Version: 2.0
Name: hmac-signature
Version: 0.2
Summary: To make a signature with the hmac algorithm. 
Home-page: https://github.com/duyixian1234/hmac_signature
Author: Yixian Du
Author-email: duyixian1233@outlook.com
License: UNKNOWN
Keywords: hmac
Platform: UNKNOWN
